meteireann/__init__.py
PyMetEireann-2021.8.0.dist-info/LICENSE
PyMetEireann-2021.8.0.dist-info/METADATA
PyMetEireann-2021.8.0.dist-info/WHEEL
PyMetEireann-2021.8.0.dist-info/top_level.txt
PyMetEireann-2021.8.0.dist-info/RECORD
