Metadata-Version: 2.1
Name: PyMetEireann
Version: 2021.8.0
Summary: A library to communicate with the Met Éireann Public Weather Forecast and Weather Warning APIs
Home-page: https://github.com/DylanGore/PyMetEireann/
Author: Dylan Gore
Author-email: hello@dylangore.ie
License: MIT
Platform: UNKNOWN
Classifier: Development Status :: 4 - Beta
Classifier: Environment :: Console
Classifier: Environment :: Other Environment
Classifier: Framework :: aiohttp
Classifier: Intended Audience :: Developers
Classifier: License :: OSI Approved :: MIT License
Classifier: Operating System :: OS Independent
Classifier: Programming Language :: Python :: 3
Classifier: Topic :: Home Automation
Classifier: Topic :: Software Development :: Libraries :: Python Modules
License-File: LICENSE
Requires-Dist: xmltodict
Requires-Dist: aiohttp
Requires-Dist: async-timeout
Requires-Dist: pytz
